unisens/__init__.py
unisens/entry.py
unisens/main.py
unisens/utils.py
pyunisens-1.5.0.dist-info/LICENSE
pyunisens-1.5.0.dist-info/METADATA
pyunisens-1.5.0.dist-info/WHEEL
pyunisens-1.5.0.dist-info/top_level.txt
pyunisens-1.5.0.dist-info/RECORD
