Metadata-Version: 2.1
Name: pyunisens
Version: 1.5.0
Summary: A python implementation of the Unisens standard
Home-page: http://github.com/Unisens/pyUnisens
Author: skjerns
License: GNU 2.0
Platform: UNKNOWN
Classifier: Programming Language :: Python :: 3
Classifier: License :: OSI Approved :: MIT License
Classifier: Operating System :: OS Independent
Requires-Python: >=3.6
License-File: LICENSE
Requires-Dist: numpy
Requires-Dist: datetime
Requires-Dist: pandas
